{"date":"2007-09-16","number_of_reviews":1,"average_stars":2.0}
{"date":"2007-09-30","number_of_reviews":1,"average_stars":4.0}
{"date":"2007-10-07","number_of_reviews":1,"average_stars":2.0}
{"date":"2007-12-02","number_of_reviews":1,"average_stars":3.0}
{"date":"2008-09-14","number_of_reviews":1,"average_stars":1.0}
{"date":"2008-10-12","number_of_reviews":1,"average_stars":4.0}
{"date":"2008-11-02","number_of_reviews":4,"average_stars":1.5}
{"date":"2008-11-16","number_of_reviews":1,"average_stars":3.0}
{"date":"2009-10-11","number_of_reviews":1,"average_stars":4.0}
{"date":"2009-10-18","number_of_reviews":1,"average_stars":3.0}
{"date":"2009-11-08","number_of_reviews":1,"average_stars":2.0}
{"date":"2009-11-15","number_of_reviews":3,"average_stars":3.33333333333}
{"date":"2009-12-06","number_of_reviews":1,"average_stars":4.0}
{"date":"2010-09-12","number_of_reviews":1,"average_stars":4.0}
{"date":"2010-09-26","number_of_reviews":1,"average_stars":5.0}
{"date":"2010-12-12","number_of_reviews":1,"average_stars":5.0}
{"date":"2011-09-20","number_of_reviews":1,"average_stars":3.0}
{"date":"2011-10-11","number_of_reviews":1,"average_stars":4.0}
{"date":"2011-10-18","number_of_reviews":2,"average_stars":3.5}
{"date":"2011-10-25","number_of_reviews":4,"average_stars":4.25}
{"date":"2011-11-15","number_of_reviews":2,"average_stars":2.0}
{"date":"2011-11-22","number_of_reviews":1,"average_stars":2.0}
{"date":"2011-12-06","number_of_reviews":1,"average_stars":2.0}
{"date":"2011-12-20","number_of_reviews":3,"average_stars":3.0}
{"date":"2011-12-27","number_of_reviews":1,"average_stars":4.0}
{"date":"2012-09-09","number_of_reviews":4,"average_stars":3.25}
{"date":"2012-09-16","number_of_reviews":4,"average_stars":2.75}
{"date":"2012-09-23","number_of_reviews":1,"average_stars":3.0}
{"date":"2012-09-30","number_of_reviews":1,"average_stars":4.0}
{"date":"2012-12-16","number_of_reviews":8,"average_stars":4.0}
{"date":"2013-09-15","number_of_reviews":6,"average_stars":2.66666666667}
{"date":"2013-09-29","number_of_reviews":6,"average_stars":3.16666666667}
{"date":"2013-10-06","number_of_reviews":1,"average_stars":2.0}
{"date":"2013-10-27","number_of_reviews":1,"average_stars":4.0}
{"date":"2013-11-10","number_of_reviews":6,"average_stars":2.33333333333}
{"date":"2013-11-17","number_of_reviews":5,"average_stars":3.4}
{"date":"2013-11-24","number_of_reviews":4,"average_stars":3.75}
{"date":"2013-12-08","number_of_reviews":3,"average_stars":3.0}
{"date":"2013-12-15","number_of_reviews":2,"average_stars":4.0}
{"date":"2014-09-08","number_of_reviews":5,"average_stars":3.0}
{"date":"2014-09-14","number_of_reviews":9,"average_stars":2.55555555556}
{"date":"2014-09-21","number_of_reviews":4,"average_stars":4.0}
{"date":"2014-10-12","number_of_reviews":3,"average_stars":4.33333333333}
{"date":"2014-10-19","number_of_reviews":3,"average_stars":1.33333333333}
{"date":"2014-10-26","number_of_reviews":4,"average_stars":2.5}
{"date":"2014-11-02","number_of_reviews":2,"average_stars":4.0}
{"date":"2014-11-09","number_of_reviews":6,"average_stars":3.33333333333}
{"date":"2014-11-16","number_of_reviews":6,"average_stars":3.66666666667}
{"date":"2014-12-07","number_of_reviews":2,"average_stars":3.5}
{"date":"2014-12-11","number_of_reviews":3,"average_stars":3.33333333333}